KElbowFinder/__init__.py
KElbowFinder/elbow.py
kelbowfinder-0.1.0.dist-info/METADATA
kelbowfinder-0.1.0.dist-info/WHEEL
kelbowfinder-0.1.0.dist-info/top_level.txt
kelbowfinder-0.1.0.dist-info/RECORD
