Metadata-Version: 2.4
Name: KElbowFinder
Version: 0.1.0
Summary: Automatically find the optimal number of clusters (k) for KMeans using the Elbow Method and visualize the result.
Home-page: https://github.com/Zahraaxikmah123/kmeans_elbow_finder.git
Author: Mohamed Adan, Sara Iidle, Nasteha Nor
Author-email: zaaraxikmahiidle388@gmail.com
Classifier: Programming Language :: Python :: 3
Classifier: License :: OSI Approved :: MIT License
Classifier: Operating System :: OS Independent
Requires-Python: >=3.7
Requires-Dist: scikit-learn
Requires-Dist: matplotlib
Requires-Dist: pandas
Requires-Dist: numpy
Requires-Dist: kneed
Dynamic: author
Dynamic: author-email
Dynamic: classifier
Dynamic: home-page
Dynamic: requires-dist
Dynamic: requires-python
Dynamic: summary
